DHN/Graphics.py
DHN/DrawParameterGraph.py
DHN/__init__.py
DHN/_dhn.cpython-310-darwin.so
DHN/Resources/logic/3_1_3n_0p.dat
DHN/Resources/logic/3_1_3n_0p_E.dat
DHN/Resources/logic/3_1_2n_1p.dat
DHN/Resources/logic/4_1_2n_2p.dat
DHN/Resources/logic/4_1_1n_3p_E.dat
DHN/Resources/logic/2_1_0n_2p_E.dat
DHN/Resources/logic/2_1_0n_2p.dat
DHN/Resources/logic/5_1_4n_1p_E.dat
DHN/Resources/logic/5_1_2n_3p_E.dat
DHN/Resources/logic/4_1_0n_4p.dat
DHN/Resources/logic/5_1_1n_4p_E.dat
DHN/Resources/logic/4_1_2n_2p_E.dat
DHN/Resources/logic/4_1_4n_0p_E.dat
DHN/Resources/logic/1_1_1n_0p_E.dat
DHN/Resources/logic/4_1_1n_3p.dat
DHN/Resources/logic/3_1_0n_3p_E.dat
DHN/Resources/logic/4_1_4n_0p.dat
DHN/Resources/logic/1_1_0n_1p_E.dat
DHN/Resources/logic/5_1_3n_2p.dat
DHN/Resources/logic/2_1_2n_0p.dat
DHN/Resources/logic/5_1_2n_3p.dat
DHN/Resources/logic/4_1_0n_4p_E.dat
DHN/Resources/logic/2_1_2n_0p_E.dat
DHN/Resources/logic/1_1_1n_0p.dat
DHN/Resources/logic/3_1_0n_3p.dat
DHN/Resources/logic/4_1_3n_1p_E.dat
DHN/Resources/logic/3_1_1n_2p.dat
DHN/Resources/logic/1_1_0n_1p.dat
DHN/Resources/logic/5_1_1n_4p.dat
DHN/Resources/logic/3_1_1n_2p_E.dat
DHN/Resources/logic/5_1_0n_5p.dat
DHN/Resources/logic/4_1_3n_1p.dat
DHN/Resources/logic/3_1_2n_1p_E.dat
DHN/Resources/logic/2_1_1n_1p.dat
DHN/Resources/logic/5_1_5n_0p.dat
DHN/Resources/logic/5_1_0n_5p_E.dat
DHN/Resources/logic/5_1_4n_1p.dat
DHN/Resources/logic/5_1_3n_2p_E.dat
DHN/Resources/logic/0_1_0n_0p_E.dat
DHN/Resources/logic/2_1_1n_1p_E.dat
DHN/Resources/logic/5_1_5n_0p_E.dat
DHN/_dhn/DHN.cpp
DHN/_dhn/include/common.h
DHN/_dhn/include/DHN.hpp
DHN/_dhn/include/DHN.h
DHN/_dhn/include/Dynamics/MorseGraph.hpp
DHN/_dhn/include/Dynamics/MorseDecomposition.h
DHN/_dhn/include/Dynamics/MorseDecomposition.hpp
DHN/_dhn/include/Dynamics/MorseGraph.h
DHN/_dhn/include/Dynamics/Annotation.hpp
DHN/_dhn/include/Dynamics/Annotation.h
DHN/_dhn/include/Phase/DomainGraph.hpp
DHN-0.1.1.dist-info/RECORD
DHN-0.1.1.dist-info/LICENSE
DHN-0.1.1.dist-info/WHEEL
DHN-0.1.1.dist-info/top_level.txt
DHN-0.1.1.dist-info/METADATA
