Metadata-Version: 2.1
Name: DHN
Version: 0.1.1
Summary: DHN (Dynamics of Hopfield Networks)
Home-page: https://github.com/marciogameiro/DHN
Author: Marcio Gameiro
Author-email: marciogameiro@gmail.com
License-File: LICENSE
